[
    {
        "name": "Twitter",
        "link": "https://twitter.com/sennoidal",
        "image": "images/social/twitter.svg"
    },
    {
        "name": "Instagram",
        "link": "https://instagram.com/sennoidal",
        "image": "images/social/instagram.svg"
    },
    {
        "name": "YouTube",
        "link": "https://youtube.com/",
        "image": "images/social/youtube.svg"
    },
    {
        "name": "GitHub",
        "link": "https://github.com/sennoidal",
        "image": "images/social/github.svg"
    }
]
